<internal_dependencies>
    <!-- Neurotrauma orig -->
    <dependency steamID="2776270649">
        <conflict>
            <mod steamID="3190189044" />
        </conflict>
    </dependency>

    <!-- Neurotrauma fork -->
    <dependency steamID="3190189044">
        <conflict>
            <mod steamID="2776270649" />
        </conflict>
    </dependency>

    <!-- 
        Neurotrauma addons 
    -->
    <!-- NT Cybernetics -->
    <dependency steamID="2788543375"><requirement><mod steamID="3190189044" /></requirement></dependency>

    <!-- NT Pharmacy orig -->
    <dependency steamID="2804655816"><requirement><mod steamID="3190189044" /></requirement></dependency>

    <!-- NT Symbiote -->
    <dependency steamID="3068776800"><requirement><mod steamID="3190189044" /></requirement></dependency>

    <!-- NT Unstunned -->
    <dependency steamID="2813054904"><requirement><mod steamID="3190189044" /></requirement></dependency>

    <!-- NT Cybernetics Enhanced -->
    <dependency steamID="3324062208"><requirement><mod steamID="3190189044" /></requirement></dependency>

    <!-- NT Eyes -->
    <dependency steamID="3294574390"><requirement><mod steamID="3190189044" /></requirement></dependency>

    <!-- NT Informative Descriptions -->
    <dependency steamID="3294275235"><requirement><mod steamID="3190189044" /></requirement></dependency>

    <!-- NT Pharmacy fork -->
    <dependency steamID="3247838390"><requirement><mod steamID="3190189044" /></requirement></dependency>

    <!-- NT Lobotomy -->
    <dependency steamID="3326291860"><requirement><mod steamID="3190189044" /></requirement></dependency>

    <!-- NT Surgery Sepsis -->
    <dependency steamID="3277152029"><requirement><mod steamID="3190189044" /></requirement></dependency>

    <!-- Doctor Javier's Surgical Bomb - NT Expansion -->
    <dependency steamID="2982955270"><requirement><mod steamID="3190189044" /></requirement></dependency>

    <!-- NT Infections -->
    <dependency steamID="3286567141"><requirement><mod steamID="3190189044" /></requirement></dependency>

    <!-- NT Blahaj Plus -->
    <dependency steamID="2936664151"><requirement><mod steamID="3190189044" /></requirement></dependency>

    <!-- NT Better Scanner -->
    <dependency steamID="3301984133"><requirement><mod steamID="3190189044" /></requirement></dependency>
</internal_dependencies>
